{
  "parent": "minecraft:recipes/root",
  "rewards": {
    "recipes": [
      "zycraft:quartz_crystal_block"
    ]
  },
  "criteria": {
    "has_quartz_crystal": {
      "trigger": "minecraft:inventory_changed",
      "conditions": {
        "items": [
          {
            "item": "zycraft:quartz_crystal"
          }
        ]
      }
    },
    "has_the_recipe": {
      "trigger": "minecraft:recipe_unlocked",
      "conditions": {
        "recipe": "zycraft:quartz_crystal_block"
      }
    }
  },
  "requirements": [
    [
      "has_quartz_crystal",
      "has_the_recipe"
    ]
  ]
}